fairclient/__init__.py
fairclient/_version.py
fairclient/basicclient.py
fairclient/fdpclient.py
fairclient/sparqlclient.py
fairclient/utils.py
fairclient-1.0.1.dist-info/METADATA
fairclient-1.0.1.dist-info/WHEEL
fairclient-1.0.1.dist-info/licenses/LICENSE.txt
fairclient-1.0.1.dist-info/RECORD
