Metadata-Version: 2.3
Name: fairclient
Version: 1.0.1
Summary: A FAIR Data Point client written in Python
Project-URL: Documentation, https://github.com/health-ri/fairclient#readme
Project-URL: Issues, https://github.com/health-ri/fairclient/issues
Project-URL: Source, https://github.com/health-ri/fairclient
Author-email: Mark Janse <mark.janse@health-ri.nl>
License-Expression: MIT
License-File: LICENSE.txt
Keywords: FDP
Classifier: Development Status :: 4 - Beta
Classifier: Programming Language :: Python
Classifier: Programming Language :: Python :: 3.8
Classifier: Programming Language :: Python :: 3.9
Classifier: Programming Language :: Python :: 3.10
Classifier: Programming Language :: Python :: 3.11
Classifier: Programming Language :: Python :: 3.12
Classifier: Programming Language :: Python :: Implementation :: CPython
Classifier: Programming Language :: Python :: Implementation :: PyPy
Requires-Python: >=3.8
Requires-Dist: rdflib~=7.0.0
Requires-Dist: sparqlwrapper~=2.0
